Metadata-Version: 2.4
Name: avocado-framework-plugin-resultsdb
Version: 113.0
Summary: Avocado Plugin to propagate Job results to Resultsdb
Home-page: http://avocado-framework.github.io/
Author: Avocado Developers
Author-email: avocado-devel@redhat.com
Requires-Dist: avocado-framework==113.0
Requires-Dist: resultsdb-api==2.1.5
Requires-Dist: urllib3<2.3.0; python_version < "3.9"
Dynamic: author
Dynamic: author-email
Dynamic: description
Dynamic: description-content-type
Dynamic: home-page
Dynamic: requires-dist
Dynamic: summary
